README.rst
setup.py
stanczyk/__init__.py
stanczyk/_version.py
stanczyk/console.py
stanczyk/credentials.py
stanczyk/exercises.py
stanczyk/protocol.py
stanczyk/proxy.py
stanczyk/util.py
stanczyk.egg-info/PKG-INFO
stanczyk.egg-info/SOURCES.txt
stanczyk.egg-info/dependency_links.txt
stanczyk.egg-info/top_level.txt
stanczyk.egg-info/zip-safe
stanczyk/test/__init__.py
stanczyk/test/test_console.py
stanczyk/test/test_credentials.py
stanczyk/test/test_exercises.py
stanczyk/test/test_protocol.py
stanczyk/test/test_proxy.py
stanczyk/test/util.py