Metadata-Version: 1.1
Name: stanczyk
Version: 0.1.0
Summary: Client software for the exercises in Crypto 101, the introductory book on cryptography.
Home-page: https://github.com/crypto101/stanczyk
Author: Laurens Van Houtven
Author-email: _@lvh.io
License: ISC
Keywords: crypto twisted
Platform: UNKNOWN
Classifier: Development Status :: 3 - Alpha
Classifier: Environment :: Console
Classifier: Framework :: Twisted
Classifier: Intended Audience :: Education
Classifier: License :: OSI Approved :: ISC License (ISCL)
Classifier: Programming Language :: Python :: 2 :: Only
Classifier: Programming Language :: Python :: 2.6
Classifier: Programming Language :: Python :: 2.7
Classifier: Topic :: Education
Classifier: Topic :: Games/Entertainment
Classifier: Topic :: Security :: Cryptography
